bibt/gcp/asset/__init__.py
bibt/gcp/asset/classes.py
bibt/gcp/asset/version.py
bibt_gcp_asset-0.1.54.dist-info/METADATA
bibt_gcp_asset-0.1.54.dist-info/WHEEL
bibt_gcp_asset-0.1.54.dist-info/licenses/LICENSE
bibt_gcp_asset-0.1.54.dist-info/RECORD
