Metadata-Version: 2.4
Name: bibt-gcp-asset
Version: 0.1.54
Summary: Functionality often used by BITS Blue Team (GCP Asset Module).
Project-URL: Bug Tracker, https://github.com/broadinstitute/bibt-gcp-asset/issues
Project-URL: Documentation, https://bibt-gcp-asset.readthedocs.io/en/latest/
Project-URL: Homepage, https://github.com/broadinstitute/bibt-gcp-asset
Author-email: Matthew OBrien <mobrien@broadinstitute.org>
License-File: LICENSE
Classifier: License :: OSI Approved :: MIT License
Classifier: Operating System :: OS Independent
Classifier: Programming Language :: Python :: 3
Classifier: Programming Language :: Python :: 3.9
Classifier: Programming Language :: Python :: 3.10
Classifier: Programming Language :: Python :: 3.11
Classifier: Programming Language :: Python :: 3.12
Classifier: Topic :: Security
Classifier: Topic :: Software Development :: Libraries
Classifier: Topic :: Utilities
Requires-Python: >=3.9
Requires-Dist: google-cloud-asset==3.22.0
